logpass_pytest_plugins/__init__.py
logpass_pytest_plugins/contrib/__init__.py
logpass_pytest_plugins/contrib/auto_pytest_factoryboy.py
logpass_pytest_plugins/contrib/channels.py
logpass_pytest_plugins/contrib/flask.py
logpass_pytest_plugins/contrib/rest_framework.py
logpass_pytest_plugins/py.typed
logpass_pytest_plugins-0.1.1.dist-info/WHEEL
logpass_pytest_plugins-0.1.1.dist-info/METADATA
logpass_pytest_plugins-0.1.1.dist-info/RECORD
