Metadata-Version: 2.1
Name: logpass-pytest-plugins
Version: 0.1.1
Summary: Pytest's plugins crafted by LogPass
Home-page: https://dev.logpass.me
Keywords: pytest,pytest-plugin,django,channels,factory_boy,logpass,tests,test
Author: Bartosz Barwikowski
Author-email: bartosz.barwikowski@logpass.me
Requires-Python: >=3.7.0,<4.0.0
Classifier: Development Status :: 4 - Beta
Classifier: Intended Audience :: Developers
Classifier: Operating System :: OS Independent
Classifier: Programming Language :: Python :: 3
Classifier: Programming Language :: Python :: 3.10
Classifier: Programming Language :: Python :: 3.7
Classifier: Programming Language :: Python :: 3.8
Classifier: Programming Language :: Python :: 3.9
Classifier: Topic :: Software Development :: Libraries :: Python Modules
Classifier: Topic :: Software Development :: Testing
Provides-Extra: auto_pytest_factoryboy
Provides-Extra: channels
Provides-Extra: flask
Provides-Extra: rest_framework
Requires-Dist: channels (>=3.0.0); extra == "channels"
Requires-Dist: djangorestframework (>=3.13.1,<4.0.0); extra == "rest_framework"
Requires-Dist: flask (>=2.1.2,<3.0.0); extra == "flask"
Requires-Dist: pytest (>=6.2.0)
Requires-Dist: pytest-asyncio (>=0.17.2,<0.19.0); extra == "channels"
Requires-Dist: pytest-django (>=4.5.2,<5.0.0); extra == "channels"
Requires-Dist: pytest-factoryboy (>=2.5.0,<3.0.0); extra == "auto_pytest_factoryboy"
Project-URL: Repository, https://github.com/LogPass/logpass_pytest_plugins
